Workbook

Sheet Instructions
A1: MS Excel Practical Exam
A2: Total Questions: 30
A3: Difficulty Level: Medium
A4: Syllabus: Formulas, Logical Functions, Lookups, INDEX-MATCH, Pivot Tables & Charts, Data Analysis
A5: Attempt all questions using appropriate Excel tools/functions.

Sheet Sales_Data
A1: Order_ID | B1: Region | C1: Salesperson | D1: Product | E1: Quantity | F1: Unit_Price | G1: Sales_Date | H1: Product_Category | I1: Ans 1 | J1: Ans 2 | K1: Ans 3 | L1: Ans 5 | M1: Ans 6 | O1: Ans 7 | P1: Ans 8 | R1: Ans 9 | S1: Ans 10 | U1: Ans 16 | W1: Ans 17 | Y1: Ans 18 | AA1: Ans 23 | AB1: Ans 24 | AD1: Ans 26
A2: 301 | B2: North | C2: Amit | D2: Laptop | E2: 2 | F2: 45000 | G2: 05-01-2025 | H2: Desk Gaget | I2: =F2*E2 -> 90000 | J2: =I2*VLOOKUP(D2,Product_Master!A:C,3,FALSE)/100 -> 16200 | K2: =I2+J2 -> 106200 | L2: =COUNTA(D2:D7) -> 6 | M2: East | N2: =SUMIF($B$2:$B$7,M2,$F$2:$F$7) -> 18000 | O2: =IF(E2<=3,"low","High") -> low | P2: MIN | Q2: =MIN(K2:K7) -> 53100 | R2: =TEXT(G2,"MMMM") -> January | S2: 53100 | T2: 12-01-2025 | U2: Row Labels | V2: Sum of Ans 1 | W2: Row Labels | X2: Sum of Ans 1 | Y2: Region | Z2: (All) | AA2: =LEFT(C2,2) -> Am | AB2: =K2 -> 106200 | AD2: =COUNTIFS(B1:D7,"Laptop",B1:D7,"North") -> 0
A3: 302 | B3: South | C3: Riya | D3: Mobile | E3: 5 | F3: 15000 | G3: 45664 | H3: Hand Gaget | I3: =F3*E3 -> 75000 | J3: =I3*VLOOKUP(D3,Product_Master!A:C,3,FALSE)/100 -> 9000 | K3: =I3+J3 -> 84000 | M3: West | N3: =SUMIF($B$2:$B$7,M3,$F$2:$F$7) -> 45000 | O3: =IF(E3<=3,"low","High") -> High | P3: MAX | Q3: =MAX(K2:K7) -> 106200 | R3: =TEXT(G3,"MMMM") -> January | S3: 60480 | T3: 10-01-2025 | U3: Laptop | V3: 225000 | W3: East | X3: 54000 | AA3: =LEFT(C3,2) -> Ri | AB3: =K3 -> 84000
A4: 303 | B4: East | C4: Kunal | D4: Tablet | E4: 3 | F4: 18000 | G4: 10-01-2025 | H4: Hand Gaget | I4: =F4*E4 -> 54000 | J4: =I4*VLOOKUP(D4,Product_Master!A:C,3,FALSE)/100 -> 6480 | K4: =I4+J4 -> 60480 | M4: North | N4: =SUMIF($B$2:$B$7,M4,$F$2:$F$7) -> 60000 | O4: =IF(E4<=3,"low","High") -> low | R4: =TEXT(G4,"MMMM") -> January | S4: 67200 | T4: 15-01-2025 | U4: Mobile | V4: 135000 | W4: North | X4: 150000 | Y4: Row Labels | Z4: Sum of Unit_Price | AA4: =LEFT(C4,2) -> Ku | AB4: =K4 -> 60480
A5: 304 | B5: West | C5: Neha | D5: Laptop | E5: 1 | F5: 45000 | G5: 12-01-2025 | H5: Desk Gaget | I5: =F5*E5 -> 45000 | J5: =I5*VLOOKUP(D5,Product_Master!A:C,3,FALSE)/100 -> 8100 | K5: =I5+J5 -> 53100 | M5: South | N5: =SUMIF($B$2:$B$7,M5,$F$2:$F$7) -> 60000 | O5: =IF(E5<=3,"low","High") -> low | R5: =TEXT(G5,"MMMM") -> January | S5: 84000 | T5: 07-01-2025 | U5: Tablet | V5: 54000 | W5: South | X5: 165000 | Y5: Laptop | Z5: 135000 | AA5: =LEFT(C5,2) -> Ne | AB5: =K5 -> 53100
A6: 305 | B6: North | C6: Amit | D6: Mobile | E6: 4 | F6: 15000 | G6: 15-01-2025 | H6: Hand Gaget | I6: =F6*E6 -> 60000 | J6: =I6*VLOOKUP(D6,Product_Master!A:C,3,FALSE)/100 -> 7200 | K6: =I6+J6 -> 67200 | O6: =IF(E6<=3,"low","High") -> High | R6: =TEXT(G6,"MMMM") -> January | S6: 106200 | T6: 05-01-2025 | U6: Grand Total | V6: 414000 | W6: West | X6: 45000 | Y6: Mobile | Z6: 30000 | AA6: =LEFT(C6,2) -> Am | AB6: =K6 -> 67200
A7: 306 | B7: South | C7: Riya | D7: Laptop | E7: 2 | F7: 45000 | G7: 18-01-2025 | H7: Desk Gaget | I7: =F7*E7 -> 90000 | J7: =I7*VLOOKUP(D7,Product_Master!A:C,3,FALSE)/100 -> 16200 | K7: =I7+J7 -> 106200 | O7: =IF(E7<=3,"low","High") -> low | R7: =TEXT(G7,"MMMM") -> January | S7: 106200 | T7: 18-01-2025 | W7: Grand Total | X7: 414000 | Y7: Tablet | Z7: 18000 | AA7: =LEFT(C7,2) -> Ri | AB7: =K7 -> 106200
H8: Ans 4 | I8: =SUM(I$2:I$7) -> 414000 | J8: =SUM(J$2:J$7) -> 63180 | K8: =SUM(K$2:K$7) -> 477180 | Y8: Grand Total | Z8: 183000
F12: 11 | G12: Use INDEX-MATCH to fetch Product Category.
F13: 25 | G13: Filter orders where Product is Laptop and Quantity > 1.
F21: 26 | G21: Use COUNTIFS to count Laptop orders in North region.
F22: 27 | G22: Use ROUND to round Unit_Price to nearest thousand.
F23: 28 | G23: Remove duplicate records if present.
F24: 29 | G24: Freeze top row in Sales_Data sheet.
F25: 30 | G25: Protect the Student_Marks sheet.

Sheet Product_Master
A1: Product | B1: Category | C1: GST_% | D1: Product_Category
A2: Laptop | B2: Electronics | C2: 18 | D2: Desk Gaget
A3: Mobile | B3: Electronics | C3: 12 | D3: Hand Gaget
A4: Tablet | B4: Electronics | C4: 12 | D4: Hand Gaget

Sheet Student_Marks
A1: Student_ID | B1: Name | C1: Maths | D1: Statistics | E1: Excel | F1: Attendance_% | H1: Ans 12 | I1: Ans 13 | J1: Ans 14 | K1: Ans 15 | L1: Ans 19 | Q1: Ans 20 | R1: Ans 21 | S1: Ans 22 | T1: Ans 23
A2: 1 | B2: Rahul | C2: 78 | D2: 82 | E2: 85 | F2: 92 | H2: =AVERAGE(C2:E2) -> 81.666667 | I2: =IF(H2>$H$7, "Topper", "Avg student") -> Topper | J2: =COUNTIF(F2:F6,">90") -> 3 | K2: =IF(F2>=85,"Eligible","NE") -> Eligible | Q2: =MEDIAN(D2:D6) -> 82 | S2: =_xlfn.CONCAT(A2,B2) -> 1Rahul
A3: 2 | B3: Sneha | C3: 88 | D3: 91 | E3: 90 | F3: 96 | H3: =AVERAGE(C3:E3) -> 89.666667 | I3: =IF(H3>$H$7, "Topper", "Avg student") -> Topper | K3: =IF(F3>=85,"Eligible","NE") -> Eligible | S3: =_xlfn.CONCAT(A3,B3) -> 2Sneha
A4: 3 | B4: Arjun | C4: 65 | D4: 70 | E4: 72 | F4: 85 | H4: =AVERAGE(C4:E4) -> 69 | I4: =IF(H4>$H$7, "Topper", "Avg student") -> Avg student | K4: =IF(F4>=85,"Eligible","NE") -> Eligible | S4: =_xlfn.CONCAT(A4,B4) -> 3Arjun
A5: 4 | B5: Pooja | C5: 92 | D5: 89 | E5: 94 | F5: 98 | H5: =AVERAGE(C5:E5) -> 91.666667 | I5: =IF(H5>$H$7, "Topper", "Avg student") -> Topper | K5: =IF(F5>=85,"Eligible","NE") -> Eligible | S5: =_xlfn.CONCAT(A5,B5) -> 4Pooja
A6: 5 | B6: Vikas | C6: 55 | D6: 60 | E6: 58 | F6: 80 | H6: =AVERAGE(C6:E6) -> 57.666667 | I6: =IF(H6>$H$7, "Topper", "Avg student") -> Avg student | K6: =IF(F6>=85,"Eligible","NE") -> NE | S6: =_xlfn.CONCAT(A6,B6) -> 5Vikas
G7: Grand AVG | H7: =AVERAGE(H2:H6) -> 77.933333
H21: 21 | I21: Find Standard Deviation of Excel marks.

Sheet Questions
A1: Sr.No | B1: Task | D1: Marks
A2: 1 | B2: Calculate Total Sales for each order (Quantity × Unit_Price). | D2: 2
A3: 2 | B3: Calculate GST Amount using VLOOKUP from Product_Master. | D3: 2
A4: 3 | B4: Find Final Amount payable (Total Sales + GST). | D4: 2
A5: 4 | B5: Find Grand Total of Final Amount. | D5: 2
A6: 5 | B6: Count total number of orders using COUNTA. | D6: 2
A7: 6 | B7: Find Region-wise total sales using SUMIF. | D7: 2
A8: 7 | B8: Use IF to classify Quantity as High (>3) or Low (<=3). | D8: 2
A9: 8 | B9: Find the maximum and minimum Final Amount. | D9: 2
A10: 9 | B10: Extract month name from Sales_Date. | D10: 2
A11: 10 | B11: Sort Sales_Data by Final Amount (Descending). | D11: 2
A12: 11 | B12: Use INDEX-MATCH to fetch Product Category. | D12: 2
A13: 12 | B13: Calculate average marks of each student. | D13: 2
... A31: 30 | B31: Protect the Student_Marks sheet. | D31: 2
D33: =SUM(D2:D31) -> 60
